Src/terminal.v
module terminal(
        input   wire            clk,
        input   wire            reset_n,
        input   wire            we,
        input   wire    [31:0]  addr,
        input   wire    [31:0]  data_write,
        output  reg     [7:0]   terminal_bus
);

    // reg [7:0] terminal_bus;
    reg [127:0] terminal_block;

    integer i;
    always @(posedge clk or negedge reset_n)
    begin
        if(!reset_n)
        begin
            terminal_bus = 8'h0;
            terminal_block = 128'h0;
        end
        else
        begin
            /*  write  */
            if(we && (addr[31:8] == 24'h1))
            begin
                terminal_bus <= data_write[7:0];
                terminal_block <= (terminal_block << 8) + data_write[7:0];
            end
        end
    end


endmodule // terminal

Src/ram.v
module ram(
        input   wire            clk,
        input   wire            reset_n,
        input   wire            we,
        input   wire    [31:0]  addr,
        output  wire    [31:0]  data_read,
        input   wire    [31:0]  data_write
    );

    reg [31:0] ram_block[255:0];

    /*  read  */
    assign data_read = ram_block[addr];

    integer i;
    always @(posedge clk or negedge reset_n)
    begin
        if(!reset_n)
        begin
            /*  reset  */
            for(i=0;i<255;i=i+1)
                ram_block[i] = 32'h0;
        end
        else
        begin
            /*  write  */
            if(we && (addr[31:8] == 24'h0))
                ram_block[addr] <= data_write;
        end
    end

endmodule // ram

Src/alu.v
module alu(
        input   wire    [31:0]  A,
        input   wire    [31:0]  B,
        input   wire    [2:0]   F,
        output  reg     [31:0]  Y,
        output  wire    	    zero
    );

    /*  Y  */
    always@(*)
    begin 
        case(F)
            3'b000:     Y = A & B;
            3'b001:     Y = A | B;
            3'b010:     Y = A + B;

            3'b100:     Y = A << B[4:0];
            3'b101:     Y = A >> B[4:0];

            3'b110:     Y = A - B;
            3'b111:     Y = (A < B) ? 32'b1 : 32'b0;

            default:    Y = 32'hxxxxxxxx;
        endcase
    end

    /*  zero  */
    assign zero = (A == B) ? 1'b1 : 1'b0;

endmodule // alu

Src/register.v
module register(
        input   wire            clk,
        input   wire            reset_n,

        input   wire    [4:0]   addr1,
        output  wire    [31:0]  read1,

        input   wire    [4:0]   addr2,
        output  wire    [31:0]  read2,

        input   wire            we3,
        input   wire    [4:0]   addr3,
        input   wire    [31:0]  write3
    );

    reg [31:0] register_block [31:0];

    assign read1 = (addr1==5'b11111) ? 31'h0 : register_block[addr1];
    assign read2 = (addr2==5'b11111) ? 31'h0 : register_block[addr2];

    integer i;
    always @(posedge clk or negedge reset_n)
    begin
        if(!reset_n)
        begin
            /*  reset  */
            for(i=0;i<32;i=i+1)
                register_block[i] = 32'h0;
        end
        else
        begin
            /*  write  */
            if(we3 && (addr3 != 5'b11111))
                register_block[addr3] <= write3;
        end
    end

endmodule // register

Src/cu.v
/*  Control Unit  */
module cu(
        input   wire            reset_n,

        input   wire    [5:0]   op,
        input   wire    [5:0]   funct,

        output  reg             reg_write,
        output  reg             reg_dst,
        output  reg             alu_src,
        output  reg             branch,
        output  reg             mem_write,
        output  reg             mem_to_reg,
        output  reg     [2:0]   alu_control
    );

    reg [1:0] alu_op;

    always @(*)
    begin
		if(!reset_n)
		begin
            reg_write       = 1'b0;
            reg_dst         = 1'b0;
            alu_src         = 1'b0;
            branch          = 1'b0;
            mem_write       = 1'b0;
            mem_to_reg      = 1'b0;
            alu_op          = 2'b00;
        end
        else
        begin
            /*  main decoder  */
            case(op)
                /*  R-type instructions  */
                6'b000000:
                begin
                    reg_write   = 1'b1;
                    reg_dst     = 1'b1;
                    alu_src     = 1'b0;
                    branch      = 1'b0;
                    mem_write   = 1'b0;
                    mem_to_reg  = 1'b0;
                    alu_op      = 2'b10;
                end

                /*  Memory instructions - lw  */ 
                6'b100011:
                begin
                    reg_write   = 1'b1;
                    reg_dst     = 1'b0;
                    alu_src     = 1'b1;
                    branch      = 1'b0;
                    mem_write   = 1'b0;
                    mem_to_reg  = 1'b1;
                    alu_op      = 2'b00;
                end

                /*  Memory instructions - sw  */ 
                6'b101011:
                begin
                    reg_write   = 1'b0;
                    reg_dst     = 1'b0; // X
                    alu_src     = 1'b1;
                    branch      = 1'b0;
                    mem_write   = 1'b1;
                    mem_to_reg  = 1'b0; // X
                    alu_op      = 2'b00;
                end

                /*  Branch instructions - beq  */ 
                6'b000100:
                begin
                    reg_write   = 1'b0;
                    reg_dst     = 1'b0; // X
                    alu_src     = 1'b0;
                    branch      = 1'b1;
                    mem_write   = 1'b0;
                    mem_to_reg  = 1'b0; // X
                    alu_op      = 2'b01;
                end
                
                /*  NEW : addi  */
                6'b001000:
                begin
                    reg_write   = 1'b1;
                    reg_dst     = 1'b0;
                    alu_src     = 1'b1;
                    branch      = 1'b0;
                    mem_write   = 1'b0;
                    mem_to_reg  = 1'b0;
                    alu_op      = 2'b00;
                end
                
                /*  NEW : NOP  */
                6'b111111:
                begin
                    reg_write   = 1'b0;
                    reg_dst     = 1'b0; // X
                    alu_src     = 1'b0; // X
                    branch      = 1'b0;
                    mem_write   = 1'b0;
                    mem_to_reg  = 1'b0; // X
                    alu_op      = 2'b00;// X
                end
                
                /*  NEW : SRL/SLL(Shift Right/Left Logic)  */
                6'b000010,6'b000011:
                begin
                    reg_write   = 1'b1;
                    reg_dst     = 1'b0;
                    alu_src     = 1'b1;
                    branch      = 1'b0;
                    mem_write   = 1'b0;
                    mem_to_reg  = 1'b0;
                    alu_op      = 2'b11;
                end
                
                default:
                begin
                    reg_write   = 1'hx;
                    reg_dst     = 1'hx;
                    alu_src     = 1'hx;
                    branch      = 1'hx;
                    mem_write   = 1'hx;
                    mem_to_reg  = 1'hx;
                    alu_op      = 2'bxx;
                end	 
            endcase
        end
    end

    /*  ALU Decoder  */
    always@(*)
    begin
        case (alu_op)
            2'b00: 
            begin
                alu_control = 3'b010;   // add
            end

            2'b01: 
            begin
                alu_control = 3'b110;   // sub
            end

            2'b10: 
            begin
                case(funct)
                    6'b100000:  alu_control = 3'b010;   // add
                    6'b100010:  alu_control = 3'b110;   // sub
                    6'b100100:  alu_control = 3'b000;   // and
                    6'b100101:  alu_control = 3'b001;   // or
                    6'b101010:  alu_control = 3'b111;   // slt
                    default:    alu_control = 3'bxxx;
                endcase
            end

            2'b11:
            begin
                alu_control = {2'b10,op[0]};    // SLL,SRL
                
            end
            
            default: 
            begin
                alu_control = 3'bxxx;
            end
        endcase
    end
endmodule // cu

Src/rom.v
module rom(
        output  wire    [31:0]  dout,
        input   wire    [10:0]  addr
    );

    reg [7:0] rom_block [2047:0];

    assign dout = {rom_block[addr+0], rom_block[addr+1], rom_block[addr+2], rom_block[addr+3]};

endmodule // rom

Src/top.v
//`define __QUARTUS__
`ifndef __QUARTUS__
    `include "./Src/alu.v"
    `include "./Src/cu.v"
    `include "./Src/ram.v"
    `include "./Src/register.v"
    `include "./Src/rom.v"
    `include "./Src/terminal.v"
`endif

module top(
	input   wire            clk,
	input   wire            reset_n,
    output  wire    [7:0]   terminal_bus
);

    // ROM
    wire    [31:0]  rom_dout        ;
    wire    [10:0]  rom_addr        ;

    // CU
    wire    [5:0]   cu_op           ;
    wire    [5:0]   cu_funct        ;
    wire            cu_reg_write    ;
    wire            cu_reg_dst      ;
    wire            cu_alu_src      ;
    wire            cu_branch       ;
    wire            cu_mem_write    ;
    wire            cu_mem_to_reg   ;
    wire    [2:0]   cu_alu_control  ;

    // ALU
    wire    [31:0]  alu_A           ;
    wire    [31:0]  alu_B           ;
    wire    [2:0]   alu_F           ;
    wire    [31:0]  alu_result      ;
    wire            alu_zero        ;

    // register
    wire    [4:0]   reg_addr1       ;
    wire    [31:0]  reg_read1       ;

    wire    [4:0]   reg_addr2       ;
    wire    [31:0]  reg_read2       ;

    wire            reg_we3         ;
    wire    [4:0]   reg_addr3       ;
    wire    [31:0]  reg_write3      ;

    // RAM
    wire            ram_we          ;
    wire    [31:0]  ram_addr        ;
    wire    [31:0]  ram_read        ;
    wire    [31:0]  ram_write       ;

    // terminal
    // wire    [7:0]   terminal_bus    ;


    rom  u_rom (
        .dout           (   rom_dout        ),
        .addr           (   rom_addr        )
    );

    cu  u_cu (
        .reset_n        (   reset_n         ),
        
        .op             (   cu_op           ),
        .funct          (   cu_funct        ),

        .reg_write      (   cu_reg_write    ),
        .reg_dst        (   cu_reg_dst      ),
        .alu_src        (   cu_alu_src      ),
        .branch         (   cu_branch       ),
        .mem_write      (   cu_mem_write    ),
        .mem_to_reg     (   cu_mem_to_reg   ),
        .alu_control    (   cu_alu_control  )
    );

    register  u_register (
        .clk            (   clk             ),
        .reset_n        (   reset_n         ),
        .addr1          (   reg_addr1       ),
        .read1          (   reg_read1       ),
        .addr2          (   reg_addr2       ),
        .read2          (   reg_read2       ),
        .we3            (   reg_we3         ),
        .addr3          (   reg_addr3       ),
        .write3         (   reg_write3      )
    );

    alu  u_alu (
        .A              (   alu_A           ),
        .B              (   alu_B           ),
        .F              (   alu_F           ),
        .Y              (   alu_result      ),
        .zero           (   alu_zero        )
    );

    ram  u_ram (
        .clk            (   clk             ),
        .reset_n        (   reset_n         ),
        .we             (   ram_we          ),
        .addr           (   ram_addr        ),
        .data_read      (   ram_read        ),
        .data_write     (   ram_write       )
    );

    terminal u_terminal (
        .clk            (   clk             ),
        .reset_n        (   reset_n         ),
        .we             (   ram_we          ),
        .addr           (   ram_addr        ),
        .data_write     (   ram_write       ),
        .terminal_bus   (   terminal_bus    )
    );

    /*  IF Signal */
    wire [10:0] pc;
    reg [10:0] pc_if = 11'h0;
    wire [10:0] pc_plus4_if;
    wire [31:0] instr_if;

    /*  ID Signal  */
    reg [31:0] instr_id;
    reg [10:0] pc_plus4_id;
    wire cu_reg_write_id;
    wire cu_reg_dst_id;
    wire cu_alu_src_id;
    wire cu_branch_id;
    wire cu_mem_write_id;
    wire cu_mem_to_reg_id;
    wire [2:0] cu_alu_control_id;
    wire [31:0] reg_read1_id;
    wire [31:0] reg_read2_id;
    wire [4:0] write_addra_id;
    wire [4:0] write_addrb_id;
    wire [31:0] signimm_id;

    /*  EX Signal  */
    reg cu_reg_write_ex;
    reg cu_reg_dst_ex;
    reg cu_alu_src_ex;
    reg cu_branch_ex;
    reg cu_mem_write_ex;
    reg cu_mem_to_reg_ex;
    reg [2:0] cu_alu_control_ex;
    reg [31:0] reg_read1_ex;
    reg [31:0] reg_read2_ex;
    reg [4:0] write_addra_ex;
    reg [4:0] write_addrb_ex;
    reg [31:0] signimm_ex;
    reg [10:0] pc_plus4_ex;
    wire [31:0] src_a_ex;
    wire [31:0] src_b_ex;
    wire [31:0] ram_write_data_ex;
    wire [4:0] write_addr_ex;
    wire alu_zero_ex;
    wire [31:0] alu_result_ex;
    wire [10:0] pc_branch_adder_ex;

    /*  MEM Signal  */
    reg cu_reg_write_mem;
    reg cu_mem_to_reg_mem;
    reg cu_mem_write_mem;
    reg cu_branch_mem;
    reg alu_zero_mem;
    reg [31:0] alu_result_mem;
    reg [31:0] ram_write_data_mem;
    reg [4:0] write_addr_mem;
    reg [10:0] pc_branch_mem;
    wire pc_src_mem;
    wire ram_read_mem;

    /*  WB Signal  */
    reg cu_reg_write_wb;
    reg cu_mem_to_reg_wb;
    reg [31:0] alu_result_wb;
    reg [31:0] ram_read_wb;
    reg [4:0] write_addr_wb;
    wire [31:0] result_wb;

    /*  pc branch mux  */
    assign pc = pc_src_mem ? pc_branch_mem : pc_plus4_if;

    /*  PC Register  */
    always @(posedge clk or negedge reset_n)
	begin
        if(!reset_n)
			pc_if <= 11'h0;
        else
			pc_if <= pc;
    end

    /*  pc plus4 adder  */
    assign pc_plus4_if = pc_if + 11'h4;

    /*  rom  */
    assign rom_addr = pc_if;
    assign instr_if = rom_dout;

    /*  IF/ID Register  */
    always @(posedge clk or negedge reset_n)
	begin
        if(!reset_n)
        begin
			instr_id <= 32'h0;
            pc_plus4_id <= 11'h0;
        end
        else
        begin
			instr_id <= instr_if;
            pc_plus4_id <= pc_plus4_if;
        end
    end

    /*  cu  */
    assign cu_op    = instr_id[31:26];
    assign cu_funct = instr_id[5:0];
    assign cu_reg_write_id = cu_reg_write;
    assign cu_mem_to_reg_id = cu_mem_to_reg;
    assign cu_mem_write_id = cu_mem_write;
    assign cu_branch_id = cu_branch;
    assign cu_alu_control_id = cu_alu_control;
    assign cu_alu_src_id = cu_alu_src;
    assign cu_reg_dst_id = cu_reg_dst;

    /*  reg  */
    assign reg_addr1    = instr_id[25:21];
    assign reg_addr2    = instr_id[20:16];
    assign reg_addr3    = write_addr_wb;
    assign reg_we3      = cu_reg_write_wb;
    assign reg_write3   = result_wb;
    assign reg_read1_id = reg_read1;
    assign reg_read2_id = reg_read2;

    /*  write address mux signal  */
    assign write_addra_id = instr_id[20:16];
    assign write_addrb_id = instr_id[15:11];

    /*  sign extend  */
    assign signimm_id = {{16{instr_id[15]}},instr_id[15:0]};

    /*  ID/EX Register  */
    always @(posedge clk or negedge reset_n)
	begin
        if(!reset_n)
        begin
            cu_reg_write_ex <= 1'b0;
            cu_mem_to_reg_ex <= 1'b0;
            cu_mem_write_ex <= 1'b0;
            cu_branch_ex <= 1'b0;
            cu_alu_control_ex <= 3'b0;
            cu_alu_src_ex <= 1'b0;
            cu_reg_dst_ex <= 1'b0;
            reg_read1_ex <= 32'b0;
            reg_read2_ex <= 32'b0;
            write_addra_ex <= 5'b0;
            write_addrb_ex <= 5'b0;
            signimm_ex <= 32'b0;
            pc_plus4_ex <= 11'b0;
        end
        else
        begin
            cu_reg_write_ex <= cu_reg_write_id;
            cu_mem_to_reg_ex <= cu_mem_to_reg_id;
            cu_mem_write_ex <= cu_mem_write_id;
            cu_branch_ex <= cu_branch_id;
            cu_alu_control_ex <= cu_alu_control_id;
            cu_alu_src_ex <= cu_alu_src_id;
            cu_reg_dst_ex <= cu_reg_dst_id;
            reg_read1_ex <= reg_read1_id;
            reg_read2_ex <= reg_read2_id;
            write_addra_ex <= write_addra_id;
            write_addrb_ex <= write_addrb_id;
            signimm_ex <= signimm_id;
            pc_plus4_ex <= pc_plus4_id;
        end
    end

    /*  reg address destination mux  */
    assign write_addr_ex = cu_reg_dst_ex ? write_addrb_ex : write_addra_ex;

    /*  alu src mux  */
    assign src_a_ex = reg_read1_ex;
    assign src_b_ex = cu_alu_src_ex ? signimm_ex : reg_read2_ex;

    /*  alu  */
    assign alu_A = src_a_ex;
    assign alu_B = src_b_ex;
    assign alu_F = cu_alu_control_ex;
    assign alu_zero_ex = alu_zero;
    assign alu_result_ex = alu_result;

    /*  ram write data signal  */
    assign ram_write_data_ex = reg_read2_ex;

    /*  branch adder  */
    assign pc_branch_adder_ex = pc_plus4_ex + (signimm_ex << 2'd2);

    /*  EX/MEM Register  */
    always @(posedge clk or negedge reset_n)
	begin
        if(!reset_n)
        begin
            cu_reg_write_mem <= 1'b0;
            cu_mem_to_reg_mem <= 1'b0;
            cu_mem_write_mem <= 1'b0;
            cu_branch_mem <= 1'b0;
            alu_zero_mem <= 1'b0;
            alu_result_mem <= 32'h0;
            ram_write_data_mem <= 32'h0;
            write_addr_mem <= 5'h0;
            pc_branch_mem <= 11'h0;
        end
        else
        begin
            cu_reg_write_mem <= cu_reg_write_ex;
            cu_mem_to_reg_mem <= cu_mem_to_reg_ex;
            cu_mem_write_mem <= cu_mem_write_ex;
            cu_branch_mem <= cu_branch_ex;
            alu_zero_mem <= alu_zero_ex;
            alu_result_mem <= alu_result_ex;
            ram_write_data_mem <= ram_write_data_ex;
            write_addr_mem <= write_addr_ex;
            pc_branch_mem <= pc_branch_adder_ex;
        end
    end

    /*  pc branch mux control AND   */
    assign pc_src_mem = cu_branch_mem & alu_zero_mem;

    /*  ram  */
    assign ram_we = cu_mem_write_mem;
    assign ram_addr = alu_result_mem;
    assign ram_write = ram_write_data_mem;
    assign ram_read_mem = ram_read;

    /*  MEM/WB Register  */
    always @(posedge clk or negedge reset_n)
	begin
        if(!reset_n)
        begin
            cu_reg_write_wb <= 1'b0;
            cu_mem_to_reg_wb <= 1'b0;
            alu_result_wb <= 32'b0;
            ram_read_wb <= 32'h0;
            write_addr_wb <= 5'h0;
        end
        else
        begin
            cu_reg_write_wb <= cu_reg_write_mem;
            cu_mem_to_reg_wb <= cu_mem_to_reg_mem;
            alu_result_wb <= alu_result_mem;
            ram_read_wb <= ram_read_mem;
            write_addr_wb <= write_addr_mem;
        end
    end

    /*  writeback result mux  */
    assign result_wb = cu_mem_to_reg_wb ? ram_read_wb : alu_result_wb;


    // alu to ram
    assign ram_addr = alu_result;
    assign ram_write = reg_read2;
    assign ram_we = cu_mem_write;

    assign result = cu_mem_to_reg ? ram_read : alu_result;


endmodule // top

Src/top_tb.v
`timescale 1ns/100ps

`define __QUARTUS__
`ifndef __QUARTUS__
    `include "./Src/top.v"
`else
    `define __IP_SPROM__
`endif

`define __ROM_TEST_INSTR__



module top_tb;

    reg clk = 1'b0;
    reg reset_n = 1'b1;
    wire [7:0] terminal_bus;

    /*  Instance  */
    top u_top(clk,reset_n,terminal_bus);

    always
        #10 clk = ~clk;

    integer i;
    initial
    begin
        $dumpfile("top.vcd");
        $dumpvars(0,top_tb);

        // load file
        `ifndef __QUARTUS__
            `ifdef __ROM_TEST_INSTR__
                $readmemh("../Sim/rom_test_instr.dat",u_top.u_rom.rom_block);
            `endif
        `else
            `ifndef __IP_SPROM__
                `ifdef __ROM_TEST_INSTR__
                    $readmemh("../../../../Sim/rom_test_instr.dat",u_top.u_rom.rom_block);
                `endif
             `endif
        `endif

        #20 reset_n = 1'b0;
        #20 reset_n = 1'b1;

        `ifndef __QUARTUS__
            `ifdef __ROM_TEST_INSTR__
                #350 $finish;
            `endif
        `else
            `ifdef __ROM_TEST_INSTR__
                #350 $stop;
            `endif
        `endif
    end
endmodule

Sim/top.vcd
$date
	Thu Nov 21 19:42:38 2019
$end
$version
	Icarus Verilog
$end
$timescale
	100ps
$end
$scope module top_tb $end
$var wire 8 ! terminal_bus [7:0] $end
$var reg 1 " clk $end
$var reg 1 # reset_n $end
$scope module u_top $end
$var wire 32 $ alu_A [31:0] $end
$var wire 32 % alu_B [31:0] $end
$var wire 3 & alu_F [2:0] $end
$var wire 32 ' alu_result_ex [31:0] $end
$var wire 1 ( alu_zero_ex $end
$var wire 1 " clk $end
$var wire 3 ) cu_alu_control_id [2:0] $end
$var wire 1 * cu_alu_src_id $end
$var wire 1 + cu_branch_id $end
$var wire 1 , cu_mem_to_reg_id $end
$var wire 1 - cu_mem_write_id $end
$var wire 1 . cu_reg_dst_id $end
$var wire 1 / cu_reg_write_id $end
$var wire 32 0 instr_if [31:0] $end
$var wire 1 1 pc_src_mem $end
$var wire 32 2 ram_addr [31:0] $end
$var wire 1 3 ram_we $end
$var wire 32 4 ram_write [31:0] $end
$var wire 32 5 ram_write_data_ex [31:0] $end
$var wire 5 6 reg_addr3 [4:0] $end
$var wire 32 7 reg_read1_id [31:0] $end
$var wire 32 8 reg_read2_id [31:0] $end
$var wire 1 9 reg_we3 $end
$var wire 32 : reg_write3 [31:0] $end
$var wire 1 # reset_n $end
$var wire 11 ; rom_addr [10:0] $end
$var wire 32 < src_a_ex [31:0] $end
$var wire 5 = write_addrb_id [4:0] $end
$var wire 5 > write_addra_id [4:0] $end
$var wire 5 ? write_addr_ex [4:0] $end
$var wire 8 @ terminal_bus [7:0] $end
$var wire 32 A src_b_ex [31:0] $end
$var wire 32 B signimm_id [31:0] $end
$var wire 32 C rom_dout [31:0] $end
$var wire 32 D result_wb [31:0] $end
$var wire 1 E result $end
$var wire 32 F reg_read2 [31:0] $end
$var wire 32 G reg_read1 [31:0] $end
$var wire 5 H reg_addr2 [4:0] $end
$var wire 5 I reg_addr1 [4:0] $end
$var wire 1 J ram_read_mem $end
$var wire 32 K ram_read [31:0] $end
$var wire 11 L pc_plus4_if [10:0] $end
$var wire 11 M pc_branch_adder_ex [10:0] $end
$var wire 11 N pc [10:0] $end
$var wire 1 O cu_reg_write $end
$var wire 1 P cu_reg_dst $end
$var wire 6 Q cu_op [5:0] $end
$var wire 1 R cu_mem_write $end
$var wire 1 S cu_mem_to_reg $end
$var wire 6 T cu_funct [5:0] $end
$var wire 1 U cu_branch $end
$var wire 1 V cu_alu_src $end
$var wire 3 W cu_alu_control [2:0] $end
$var wire 1 X alu_zero $end
$var wire 32 Y alu_result [31:0] $end
$var reg 32 Z alu_result_mem [31:0] $end
$var reg 32 [ alu_result_wb [31:0] $end
$var reg 1 \ alu_zero_mem $end
$var reg 3 ] cu_alu_control_ex [2:0] $end
$var reg 1 ^ cu_alu_src_ex $end
$var reg 1 _ cu_branch_ex $end
$var reg 1 ` cu_branch_mem $end
$var reg 1 a cu_mem_to_reg_ex $end
$var reg 1 b cu_mem_to_reg_mem $end
$var reg 1 c cu_mem_to_reg_wb $end
$var reg 1 d cu_mem_write_ex $end
$var reg 1 e cu_mem_write_mem $end
$var reg 1 f cu_reg_dst_ex $end
$var reg 1 g cu_reg_write_ex $end
$var reg 1 h cu_reg_write_mem $end
$var reg 1 i cu_reg_write_wb $end
$var reg 32 j instr_id [31:0] $end
$var reg 11 k pc_branch_mem [10:0] $end
$var reg 11 l pc_if [10:0] $end
$var reg 11 m pc_plus4_ex [10:0] $end
$var reg 11 n pc_plus4_id [10:0] $end
$var reg 32 o ram_read_wb [31:0] $end
$var reg 32 p ram_write_data_mem [31:0] $end
$var reg 32 q reg_read1_ex [31:0] $end
$var reg 32 r reg_read2_ex [31:0] $end
$var reg 32 s signimm_ex [31:0] $end
$var reg 5 t write_addr_mem [4:0] $end
$var reg 5 u write_addr_wb [4:0] $end
$var reg 5 v write_addra_ex [4:0] $end
$var reg 5 w write_addrb_ex [4:0] $end
$scope module u_alu $end
$var wire 32 x A [31:0] $end
$var wire 32 y B [31:0] $end
$var wire 3 z F [2:0] $end
$var wire 1 X zero $end
$var reg 32 { Y [31:0] $end
$upscope $end
$scope module u_cu $end
$var wire 6 | funct [5:0] $end
$var wire 6 } op [5:0] $end
$var wire 1 # reset_n $end
$var reg 3 ~ alu_control [2:0] $end
$var reg 2 !" alu_op [1:0] $end
$var reg 1 V alu_src $end
$var reg 1 U branch $end
$var reg 1 S mem_to_reg $end
$var reg 1 R mem_write $end
$var reg 1 P reg_dst $end
$var reg 1 O reg_write $end
$upscope $end
$scope module u_ram $end
$var wire 32 "" addr [31:0] $end
$var wire 1 " clk $end
$var wire 32 #" data_read [31:0] $end
$var wire 32 $" data_write [31:0] $end
$var wire 1 # reset_n $end
$var wire 1 3 we $end
$var integer 32 %" i [31:0] $end
$upscope $end
$scope module u_register $end
$var wire 5 &" addr1 [4:0] $end
$var wire 5 '" addr2 [4:0] $end
$var wire 5 (" addr3 [4:0] $end
$var wire 1 " clk $end
$var wire 1 # reset_n $end
$var wire 1 9 we3 $end
$var wire 32 )" write3 [31:0] $end
$var wire 32 *" read2 [31:0] $end
$var wire 32 +" read1 [31:0] $end
$var integer 32 ," i [31:0] $end
$upscope $end
$scope module u_rom $end
$var wire 11 -" addr [10:0] $end
$var wire 32 ." dout [31:0] $end
$upscope $end
$scope module u_terminal $end
$var wire 32 /" addr [31:0] $end
$var wire 1 " clk $end
$var wire 32 0" data_write [31:0] $end
$var wire 1 # reset_n $end
$var wire 1 3 we $end
$var reg 128 1" terminal_block [127:0] $end
$var reg 8 2" terminal_bus [7:0] $end
$upscope $end
$upscope $end
$upscope $end
$enddefinitions $end
#0
$dumpvars
bx 2"
bx 1"
bx 0"
bx /"
b100000000000000000000001111011 ."
b0 -"
bx ,"
bx +"
bx *"
bx )"
bx ("
bx '"
bx &"
bx %"
bx $"
bx #"
bx ""
bx !"
bx ~
bx }
bx |
bx {
bx z
bx y
bx x
bx w
bx v
bx u
bx t
bx s
bx r
bx q
bx p
bx o
bx n
bx m
b0 l
bx k
bx j
xi
xh
xg
xf
xe
xd
xc
xb
xa
x`
x_
x^
bx ]
x\
bx [
bx Z
bx Y
xX
bx W
xV
xU
bx T
xS
xR
bx Q
xP
xO
bx N
bx M
b100 L
bx K
xJ
bx I
bx H
bx G
bx F
xE
bx D
b100000000000000000000001111011 C
bx B
bx A
bx @
bx ?
bx >
bx =
bx <
b0 ;
bx :
x9
bx 8
bx 7
bx 6
bx 5
bx 4
x3
bx 2
x1
b100000000000000000000001111011 0
x/
x.
x-
x,
x+
x*
bx )
x(
bx '
bx &
bx %
bx $
1#
0"
bx !
$end
#100
b10 )
b10 W
b10 ~
b0 !"
0,
0S
0-
0R
0+
0U
1*
1V
0.
0P
1/
1O
b1000 Q
b1000 }
b111011 T
b111011 |
b0 I
b0 &"
b0 H
b0 '"
b0 >
b0 =
b1111011 B
bx L
bx 0
bx C
bx ."
bx ;
bx -"
bx l
b100 n
b100000000000000000000001111011 j
b0x o
1"
#200
0E
b0 M
1(
1X
0J
b0 :
b0 )"
b0 D
01
b0 ?
b0 %
b0 y
b0 A
b0 K
b0 #"
b0 2
b0 ""
b0 /"
b0 '
b0 Y
b0 {
b0 Q
b0 }
b0 T
b0 |
b0 B
b100 N
b0 6
b0 ("
b0 u
b0 o
b0 [
0c
09
0i
b0 k
b0 t
b0 4
b0 $"
b0 0"
b0 p
b0 Z
0\
0`
03
0e
0b
0h
b0 m
b0 s
b0 w
b0 v
b0 5
b0 r
b0 $
b0 x
b0 <
b0 q
0f
0^
b0 &
b0 z
b0 ]
0_
0d
0a
0g
b0 n
b0 j
b100 L
b100000000000000000000001111011 0
b100000000000000000000001111011 C
b100000000000000000000001111011 ."
b0 ;
b0 -"
b0 l
b0 7
b0 G
b0 +"
b0 8
b0 F
b0 *"
0*
0V
0/
0O
b0 1"
b0 !
b0 @
b0 2"
b11111111 %"
b100000 ,"
0"
0#
#300
b100000 ,"
b11111111 %"
1"
#400
bx )
bx W
bx ~
b10 !"
1.
1P
1/
1O
0"
1#
#500
xE
b10 )
b10 W
b10 ~
xJ
b0 !"
1*
1V
0.
0P
bx K
bx #"
bx 2
bx ""
bx /"
bx '
bx Y
bx {
b1000 Q
b1000 }
b111011 T
b111011 |
b1111011 B
b1000 N
1\
1f
bx &
bx z
bx ]
1g
b100 n
b100000000000000000000001111011 j
b1000 L
b100000000000010000000111001000 0
b100000000000010000000111001000 C
b100000000000010000000111001000 ."
b100 ;
b100 -"
b100 l
1"
#600
0"
#700
1E
0(
0X
b1100 N
b1000 T
b1000 |
b1 H
b1 '"
b1 >
b111001000 B
b111110000 M
b1111011 %
b1111011 y
b1111011 A
b1111011 '
b1111011 Y
b1111011 {
b1100 L
b10101111111000010000000000001010 0
b10101111111000010000000000001010 C
b10101111111000010000000000001010 ."
b1000 ;
b1000 -"
b1000 l
b1000 n
b100000000000010000000111001000 j
b100 m
b1111011 s
0f
1^
b10 &
b10 z
b10 ]
bx Z
1h
b0x o
1"
#800
0"
#900
0E
b111001000 '
b111001000 Y
b111001000 {
x3
1-
1R
0/
0O
bx :
bx )"
bx D
xJ
b11100101000 M
b111001000 %
b111001000 y
b111001000 A
b1 ?
b101011 Q
b101011 }
b1010 T
b1010 |
b11111 I
b11111 &"
b1010 B
b10000 N
bx [
19
1i
b111110000 k
bx K
bx #"
b0xx1xx10xx 2
b0xx1xx10xx ""
b0xx1xx10xx /"
b1111011 Z
0\
b1000 m
b111001000 s
b1 v
b1100 n
b10101111111000010000000000001010 j
b10000 L
b10001111111000100000000000001010 0
b10001111111000100000000000001010 C
b10001111111000100000000000001010 ."
b1100 ;
b1100 -"
b1100 l
1"
#1000
0"
#1100
xE
1,
1S
03
0-
0R
1/
1O
b1010 '
b1010 Y
b1010 {
b10100 N
b100011 Q
b100011 }
b10 H
b10 '"
b10 >
b110100 M
b1010 %
b1010 y
b1010 A
b1111011 :
b1111011 )"
b1111011 D
b10100 L
b100001100000100000 0
b100001100000100000 C
b100001100000100000 ."
b10000 ;
b10000 -"
b10000 l
b10000 n
b10001111111000100000000000001010 j
b1100 m
b1010 s
1d
0g
b11100101000 k
b1 t
b0xxx0010x0 2
b0xxx0010x0 ""
b0xxx0010x0 /"
b111001000 Z
b1111011 [
1"
#1200
0"
#1300
0E
b10 !"
0,
0S
0*
0V
1.
1P
b1111011 7
b1111011 G
b1111011 +"
b111001000 :
b111001000 )"
b111001000 D
0J
b111000 M
b10 ?
b0 Q
b0 }
b100000 T
b100000 |
b0 I
b0 &"
b11 =
b1100000100000 B
b11000 N
b1 6
b1 ("
b1 u
b111001000 [
b110100 k
b0 K
b0 #"
b1010 2
b1010 ""
b1010 /"
b1010 Z
x3
1e
0h
b10000 m
b10 v
0d
1a
1g
b10100 n
b100001100000100000 j
b11000 L
b11000010010000000100010 0
b11000010010000000100010 C
b11000010010000000100010 ."
b10100 ;
b10100 -"
b10100 l
1"
#1400
0"
#1500
1E
b110 )
b110 W
b110 ~
b0 7
b0 G
b0 +"
b0xxx00x000 4
b0xxx00x000 $"
b0xxx00x000 0"
b111001000 8
b111001000 F
b111001000 *"
xJ
b11100 N
b100010 T
b100010 |
b11 I
b11 &"
b1 H
b1 '"
b1 >
b100 =
b10000000100010 B
b10010100 M
bx K
bx #"
b0xxx101x 2
b0xxx101x ""
b0xxx101x /"
b1111011 '
b1111011 Y
b1111011 {
b11 ?
b0 %
b0 y
b0 A
b1010 :
b1010 )"
b1010 D
b11100 L
b10000100000000000000000001010 0
b10000100000000000000000001010 C
b10000100000000000000000001010 ."
b11000 ;
b11000 -"
b11000 l
b11000 n
b11000010010000000100010 j
b10100 m
b1100000100000 s
b11 w
b1111011 $
b1111011 x
b1111011 <
b1111011 q
1f
0^
0a
b111000 k
b10 t
03
0e
1b
1h
b0 o
b1010 [
09
0i
1"
#1600
0"
